[
  { "id": 0, "name": "None" },
  { "id": 100, "name": "PurchaseObjective" },
  { "id": 101, "name": "UpgradeObjective" },
  { "id": 102, "name": "PurchaseSupport" },
  { "id": 103, "name": "UpgradeSupport" },
  { "id": 104, "name": "PurchaseGuard" },
  { "id": 105, "name": "UpgradeGuard" },
  { "id": 106, "name": "MoveSquare" },
  { "id": 107, "name": "RushWithMcores" },
  { "id": 108, "name": "RecycleSquare" },
  { "id": 109, "name": "UpgradeObjectiveToLvl" },
  { "id": 110, "name": "UpgradeSupportToLvl" },
  { "id": 111, "name": "UpgradeGuardToLvl" },
  { "id": 200, "name": "SpentCurrency" },
  { "id": 201, "name": "CollectedCurrency" },
  { "id": 202, "name": "IncreaseVaultProtection" },
  { "id": 203, "name": "ProtectSalvage" },
  { "id": 300, "name": "DestroySupport" },
  { "id": 301, "name": "DestroyObjective" },
  { "id": 302, "name": "KillEnemy" },
  { "id": 303, "name": "CompleteCampaignMissions" },
  { "id": 304, "name": "CompleteMission" },
  { "id": 305, "name": "CompletePVPMissions" },
  { "id": 306, "name": "CompletePVPMissionOfDifficulty" },
  { "id": 307, "name": "PlayStyle" },
  { "id": 308, "name": "LevelUpSpeciesExpertise" },
  { "id": 309, "name": "LevelUpPlayStyleExpertise" },
  { "id": 310, "name": "KillEnemyOfTypeAndLevel" },
  { "id": 311, "name": "KillEnemyExtended" },
  { "id": 400, "name": "ObtainItem" },
  { "id": 401, "name": "OpenMechBox" },
  { "id": 402, "name": "UpgradeAnyWeapon" },
  { "id": 403, "name": "UpgradeSpecificWeapon" },
  { "id": 404, "name": "UpgradeAnyWeaponTier" },
  { "id": 405, "name": "UpgradeSpecificWeaponTier" },
  { "id": 406, "name": "ObtainCraftingComponent" },
  { "id": 407, "name": "FixTrialItemStart" },
  { "id": 408, "name": "FixTrialItemFinish" },
  { "id": 409, "name": "OpenPremiumMechBoxStart" },
  { "id": 410, "name": "OpenPremiumMechBoxFinish" },
  { "id": 500, "name": "QuestCompletion" },
  { "id": 501, "name": "QuestReplay" },
  { "id": 502, "name": "TutorialStepCompletion" },
  { "id": 600, "name": "UpdateAccount" }
]